LICENSE
README.md
setup.py
/home/runner/work/stable-fast/stable-fast/sfast/csrc/main.cpp
/home/runner/work/stable-fast/stable-fast/sfast/csrc/misc.cpp
/home/runner/work/stable-fast/stable-fast/sfast/csrc/jit/compilation_unit.cpp
/home/runner/work/stable-fast/stable-fast/sfast/csrc/jit/device_constant_override.cpp
/home/runner/work/stable-fast/stable-fast/sfast/csrc/jit/init.cpp
/home/runner/work/stable-fast/stable-fast/sfast/csrc/jit/op_input_tensor_conversion.cpp
/home/runner/work/stable-fast/stable-fast/sfast/csrc/jit/python_operator.cpp
/home/runner/work/stable-fast/stable-fast/sfast/csrc/jit/scalar_tensor_erase.cpp
/home/runner/work/stable-fast/stable-fast/sfast/csrc/operators/fused_linear.cpp
/home/runner/work/stable-fast/stable-fast/sfast/csrc/operators/cublas/cublas_gemm.cpp
/home/runner/work/stable-fast/stable-fast/sfast/csrc/operators/cudnn/cudnn_convolution.cpp
sfast/__init__.py
sfast/compilers/__init__.py
sfast/compilers/stable_diffusion_pipeline_compiler.py
sfast/cuda/__init__.py
sfast/cuda/graphs.py
sfast/dynamo/__init__.py
sfast/dynamo/backends/__init__.py
sfast/dynamo/backends/registry.py
sfast/dynamo/backends/sfast_jit.py
sfast/jit/__init__.py
sfast/jit/trace_helper.py
sfast/jit/utils.py
sfast/jit/passes/__init__.py
sfast/jit/passes/triton_passes.py
sfast/triton/__init__.py
sfast/triton/torch_ops.py
sfast/triton/modules/__init__.py
sfast/triton/modules/diffusers.py
sfast/triton/modules/native.py
sfast/triton/modules/patch.py
sfast/triton/ops/__init__.py
sfast/triton/ops/activation.py
sfast/triton/ops/conv.py
sfast/triton/ops/copy.py
sfast/triton/ops/group_norm.py
sfast/utils/__init__.py
sfast/utils/aot_printer.py
sfast/utils/compute_precision.py
sfast/utils/copy_func.py
sfast/utils/custom_python_operator.py
sfast/utils/env.py
sfast/utils/flat_tensors.py
sfast/utils/gpu_device.py
sfast/utils/memory_format.py
sfast/utils/patch.py
sfast/utils/torch_dispatch.py
sfast/utils/xformers_attention.py
sfast/utils/term_image/__init__.py
stable_fast.egg-info/PKG-INFO
stable_fast.egg-info/SOURCES.txt
stable_fast.egg-info/dependency_links.txt
stable_fast.egg-info/requires.txt
stable_fast.egg-info/top_level.txt