Metadata-Version: 2.1
Name: stable-fast
Version: 0.0.8
Summary: Stable Fast is an ultra lightweight performance optimization framework for Hugging Fase diffuser pipelines.
Home-page: https://github.com/chengzeyi/stable-fast
Author: Cheng Zeyi
Requires-Python: >=3.7
Provides-Extra: all
Provides-Extra: dev
Provides-Extra: torch
Provides-Extra: diffusers
Provides-Extra: xformers
Provides-Extra: triton
License-File: LICENSE
